gga/CSM.py
gga/__init__.py
gga_csm-0.0.3.dist-info/LICENSE
gga_csm-0.0.3.dist-info/METADATA
gga_csm-0.0.3.dist-info/WHEEL
gga_csm-0.0.3.dist-info/top_level.txt
gga_csm-0.0.3.dist-info/RECORD
