Metadata-Version: 2.1
Name: gga-csm
Version: 0.0.3
Summary: This package provides the implementation of GGA (https://arxiv.org/abs/2102.12196).
Home-page: https://github.com/mad-lab-fau/GGA-Identifying-Untrustworthy-Predictions
Author: SchwinnL
Author-email: leo.schwinn@fau.de
License: UNKNOWN
Platform: UNKNOWN
Classifier: Programming Language :: Python :: 3
Classifier: License :: OSI Approved :: MIT License
Classifier: Operating System :: OS Independent
Requires-Python: >=3.6
License-File: LICENSE
Requires-Dist: torch
